setup.py
deepcallib/__init__.py
deepcallib/deepcallib.py
deepcallib.egg-info/PKG-INFO
deepcallib.egg-info/SOURCES.txt
deepcallib.egg-info/dependency_links.txt
deepcallib.egg-info/top_level.txt